.gitignore
LICENSE
Makefile
README.md
pyproject.toml
setup.cfg
.github/pull_request_template.md
.github/ISSUE_TEMPLATE/bug_report.md
.github/ISSUE_TEMPLATE/feature_request.md
.github/workflows/coverage.yml
.github/workflows/publish_release.yml
.github/workflows/style.yml
src/orquestra/opt/convex.py
src/orquestra/opt/cost_function_augmentations.py
src/orquestra/opt/gradients.py
src/orquestra/opt/mock_objects.py
src/orquestra/opt/py.typed
src/orquestra/opt/api/__init__.py
src/orquestra/opt/api/_problem_evaluation.py
src/orquestra/opt/api/bqm_solver.py
src/orquestra/opt/api/bqm_solver_test.py
src/orquestra/opt/api/cost_function.py
src/orquestra/opt/api/example_functions.py
src/orquestra/opt/api/functions.py
src/orquestra/opt/api/optimizer.py
src/orquestra/opt/api/optimizer_test.py
src/orquestra/opt/api/problem.py
src/orquestra/opt/api/save_conditions.py
src/orquestra/opt/bqm/__init__.py
src/orquestra/opt/bqm/conversions.py
src/orquestra/opt/bqm/io.py
src/orquestra/opt/bqm/utils.py
src/orquestra/opt/history/__init__.py
src/orquestra/opt/history/recorder.py
src/orquestra/opt/optimizers/__init__.py
src/orquestra/opt/optimizers/basin_hopping.py
src/orquestra/opt/optimizers/cma_es_optimizer.py
src/orquestra/opt/optimizers/least_squares.py
src/orquestra/opt/optimizers/py.typed
src/orquestra/opt/optimizers/qiskit_optimizer.py
src/orquestra/opt/optimizers/scikit_quant_optimizer.py
src/orquestra/opt/optimizers/scipy_optimizer.py
src/orquestra/opt/optimizers/search_points_optimizer.py
src/orquestra/opt/optimizers/simple_gradient_descent.py
src/orquestra/opt/optimizers/tensor_train_optimizer.py
src/orquestra/opt/optimizers/pso/__init__.py
src/orquestra/opt/optimizers/pso/continuous_pso_optimizer.py
src/orquestra/opt/optimizers/pso/topologies.py
src/orquestra/opt/problems/__init__.py
src/orquestra/opt/problems/generators.py
src/orquestra/opt/problems/graph.py
src/orquestra/opt/problems/graph_partition.py
src/orquestra/opt/problems/max_independent_set.py
src/orquestra_opt.egg-info/PKG-INFO
src/orquestra_opt.egg-info/SOURCES.txt
src/orquestra_opt.egg-info/dependency_links.txt
src/orquestra_opt.egg-info/not-zip-safe
src/orquestra_opt.egg-info/requires.txt
src/orquestra_opt.egg-info/top_level.txt
