Metadata-Version: 2.1
Name: orquestra-opt
Version: 0.9.0
Summary: "Orquestra's library with optimization routines and interfaces"
Home-page: https://github.com/zapatacomputing/orquestra-opt
Author: Zapata Computing Inc.
Author-email: info@zapatacomputing.com,
License: Apache Software License 2.0
Classifier: Programming Language :: Python :: 3
Classifier: Operating System :: OS Independent
Classifier: License :: OSI Approved :: Apache Software License
Classifier: Topic :: Scientific/Engineering
Requires-Python: !=3.9.7,>=3.9
License-File: LICENSE
Requires-Dist: orquestra-quantum
Requires-Dist: numpy>=1.20
Requires-Dist: scipy>=1.4.1
Requires-Dist: networkx>=2.4
Provides-Extra: scikit-quant
Requires-Dist: scikit-quant>=0.8.0; extra == "scikit-quant"
Provides-Extra: cma
Requires-Dist: cma>=3.0.0; extra == "cma"
Provides-Extra: qiskit
Requires-Dist: orquestra-qiskit; extra == "qiskit"
Provides-Extra: qubo
Requires-Dist: dimod>=0.9.11; extra == "qubo"
Requires-Dist: cvxpy~=1.1.11; extra == "qubo"
Provides-Extra: ttopt
Requires-Dist: ttopt~=0.6.2; extra == "ttopt"
Requires-Dist: teneva; extra == "ttopt"
Provides-Extra: all
Requires-Dist: orquestra-opt[cma]; extra == "all"
Requires-Dist: orquestra-opt[qiskit]; extra == "all"
Requires-Dist: orquestra-opt[qubo]; extra == "all"
Requires-Dist: orquestra-opt[scikit-quant]; extra == "all"
Requires-Dist: orquestra-opt[ttopt]; extra == "all"
Provides-Extra: dev
Requires-Dist: orquestra-python-dev; extra == "dev"
Requires-Dist: orquestra-opt[all]; extra == "dev"
